podcast_summary/__init__.py
podcast_summary/download.py
podcast_summary/main.py
podcast_summary/summarize.py
podcast_summary/text_cleanup.py
podcast_summary/transcribe.py
podcast_summary/utils.py
podcast_summary/voice.py
crypto_podcast_summarizer-0.1.6.dist-info/METADATA
crypto_podcast_summarizer-0.1.6.dist-info/WHEEL
crypto_podcast_summarizer-0.1.6.dist-info/entry_points.txt
crypto_podcast_summarizer-0.1.6.dist-info/licenses/LICENSE.txt
crypto_podcast_summarizer-0.1.6.dist-info/RECORD
