Metadata-Version: 2.4
Name: crypto-podcast-summarizer
Version: 0.1.6
Summary: A tool to download, transcribe, summarize, and generate voice summaries for crypto-related podcasts.
Author-email: Abhinay Yarlagadda <Abhinay.Yarlagadda@gmail.com>
License-Expression: MIT
License-File: LICENSE.txt
Keywords: AI,crypto,podcast,summarizer,transcription
Requires-Python: >=3.8
Requires-Dist: feedparser>=6.0.10
Requires-Dist: google-genai>=0.1.0
Requires-Dist: kokoro>=0.1
Requires-Dist: numpy>=1.24.0
Requires-Dist: openai-whisper>=20231117
Requires-Dist: requests>=2.31.0
Requires-Dist: soundfile>=0.12.1
Requires-Dist: torch>=2.0.0
